README.rst
setup.py
sqlite3ndarray/__init__.py
sqlite3ndarray/sqlite.py
sqlite3ndarray.egg-info/PKG-INFO
sqlite3ndarray.egg-info/SOURCES.txt
sqlite3ndarray.egg-info/dependency_links.txt
sqlite3ndarray.egg-info/top_level.txt
test/test.py