Metadata-Version: 1.1
Name: sqlite3ndarray
Version: 0.2
Summary: sqlite3 helpers for numpy ndarrays
Home-page: http://pchanial.github.com/sqlite3ndarray
Author: Pierre Chanial
Author-email: pchanial@aneo.fr
License: UNKNOWN
Keywords: database
Platform: MacOS X
Platform: Linux
Platform: Solaris
Platform: Unix
Platform: Windows
Classifier: Programming Language :: Python
Classifier: Programming Language :: Python :: 3
Classifier: Programming Language :: Python :: 3.5
Classifier: Development Status :: 4 - Beta
Classifier: Intended Audience :: Science/Research
Classifier: Operating System :: OS Independent
Classifier: Topic :: Scientific/Engineering
